{
    "meta": {
        "req_path": "./data/AMINA/05/RE.csv",
        "test_path": "./data/AMINA/05/ST.csv",
        "mapping_path": "./data/AMINA/05/mapping.csv"
    },
    "data": {
        "links": {
            "S12": [
                "364"
            ],
            "S24": [
                "43",
                "44"
            ],
            "S70": [],
            "S73": [
                "447",
                "448"
            ],
            "S117": [
                "50"
            ],
            "S136": [],
            "S143": [
                "596"
            ],
            "S155": [
                "263"
            ],
            "S172": [
                "29"
            ],
            "S177": [
                "352"
            ],
            "S231": [
                "20",
                "219",
                "238"
            ],
            "S237": [
                "219",
                "238"
            ],
            "S259": [
                "78"
            ],
            "B31": [
                "328",
                "330"
            ],
            "B33": [
                "330"
            ],
            "B42": [
                "339",
                "340",
                "341"
            ],
            "B62": [
                "194"
            ],
            "B71": [
                "218"
            ],
            "B85": [
                "238",
                "328",
                "330",
                "442",
                "447"
            ],
            "B105": [
                "194",
                "218",
                "219",
                "238"
            ],
            "B113": [
                "26"
            ],
            "S545": [
                "86"
            ],
            "S549": [
                "90"
            ],
            "S558": [
                "99"
            ],
            "S560": [
                "101"
            ]
        },
        "err": {
            "S136": [
                "Traceback (most recent call last):\n  File \"/mimer/NOBACKUP/groups/naiss2025-22-104/REST/REST-at/src/core/rest.py\", line 357, in to_local\n    links = self._parse_intermediary_output(raw_res)\n  File \"/mimer/NOBACKUP/groups/naiss2025-22-104/REST/REST-at/src/core/rest.py\", line 409, in _parse_intermediary_output\n    return self._parse_list_output(res)\n  File \"/mimer/NOBACKUP/groups/naiss2025-22-104/REST/REST-at/src/core/rest.py\", line 499, in _parse_list_output\n    links = [\n  File \"/mimer/NOBACKUP/groups/naiss2025-22-104/REST/REST-at/src/core/rest.py\", line 500, in <listcomp>\n    self._tests_index[int(test.replace(RESTSpecification._TEST_INDEX_PREFIX, \"\"))]\nValueError: invalid literal for int() with base 10: '20-23'\n",
                "[\"T-15\", \"T-16\", \"T-20-23\", \"T-25-28\", \"T-30\"]"
            ]
        },
        "time_to_analyze": 21.19056590157561,
        "GPU": {
            "utilization": {
                "avg": 66.92207792207792,
                "std": 17.55649994623841,
                "max": 100.0
            },
            "avg_temperature": 39.62337662337662
        },
        "VRAM": {
            "max_usage_MiB": 5407.0,
            "utilization": {
                "avg": 24.142857142857142,
                "std": 14.368014811520073,
                "max": 52.0
            }
        }
    }
}